atopile_auth/__init__.py
atopile_auth/client.py
atopile_auth/data_dir_storage.py
atopile_auth/oauth_callback_server.py
atopile_auth/supabase_bearer.py
atopile_auth-0.1.3.dist-info/METADATA
atopile_auth-0.1.3.dist-info/WHEEL
atopile_auth-0.1.3.dist-info/licenses/LICENSE
atopile_auth-0.1.3.dist-info/RECORD
