Metadata-Version: 2.4
Name: atopile-auth
Version: 0.1.3
Summary: A package to help manage authentication for atopile
License-File: LICENSE
Requires-Python: >=3.13
Requires-Dist: supabase>=2.15.0
